{
    "ALREADY_LEGAL": "Dein Pokémon ist bereits legal!",
    "AUTO_LEGALIZE_ERROR": "Dein Pokémon kann nicht automatisch legalisiert werden.",
    "API_URL_REQUIRED": "You must configure the API Url in settings!",
    "BACKUP_FAIL_SAVE_1": "Speicherbank-Backup fehlgeschlagen",
    "BACKUP_FAIL_SAVE_2": "Mit dem Speichern fortfahren?",
    "BAD_CIA_FILE": "Die CIA-Datei konnte nicht gelesen werden!",
    "BAD_INJECT": "Kann nicht einfügen",
    "BAD_OPEN_BACKUP": "Konnte Backup Datei nicht öffnen!",
    "BAD_OPEN_SAVE": "Konnte Speicherstand nicht öffnen!",
    "BANK_BAD_CONVERT": "bank.bin konnte nicht gelesen werden",
    "BANK_CORRUPT": "Korrupte Bankdaten",
    "BANK_FAILED_EXIT": "Du kannst nicht verlassen wenn ein Pokémon gehalten wird!",
    "BANK_NAME_ERROR": "Konnte Boxnamen nicht speichern!",
    "BANK_SAVE_ERROR": "Konnte Lagerung nicht speichern!",
    "BP": "GP",
    "BURNED": "Verbrannt",
    "CANDIES": "Bonbons",
    "CAPSULE_INDEX_(SEALS)": "Kapsel Index (Sticker)",
    "CATCHING_ITEMS": "Fang Items",
    "CHANGE_FORM": "Form wechseln",
    "CHANGE_SPECIES": "Spezies wechseln",
    "CHECKSUM": "Prüfsumme",
    "CIA_INSTALL_FINISH_FAIL": "Update fehlgeschlagen!",
    "CIA_INSTALL_START_FAIL": "CIA konnte nicht installiert werden!",
    "CIA_UPDATE_READ_FAIL": "Fehler beim Lesen des CIA-Updates",
    "CIA_UPDATE_WRITE_FAIL": "Fehler beim Schreiben des CIA-Updates",
    "CONFIGURATION_FILE_CORRUPTED_1": "Konfigurationsdatei ist beschädigt!",
    "CONFIGURATION_INCORRECT_FORMAT": "Die Konfigurationsdatei ist falsch formatiert!",
    "CONFIGURATION_USING_DEFAULT": "Standardeinstellungen werden genutzt!",
    "CRITICAL_BANK_ERROR_1": "Schritt konnte nicht rückgängig gemacht werden!",
    "CRITICAL_BANK_ERROR_2": "Bitte informiere sofort die Entwickler!",
    "CURL_ERROR": "Fehler: Das Internet ist nicht erreichbar!",
    "DATA_RECEIVE_FAIL": "Daten konnten nicht empfangen werden.",
    "DATA_SEND_FAIL": "Daten konnten nicht gesendet werden.",
    "DO_NOT_DOWNGRADE": "Downgrade PKSM nicht!",
    "ERROR_CODE": "Fehler: 0x{:08X}",
    "FAILED_OPEN_DUMP": "Konnte die Datei zum dumpen nicht öffnen!",
    "FAIL_SAVE_COMMIT": "Konnte Speicherstand nicht übertragen!",
    "FOLDER_DOESNT_EXIST": "Ordner existiert nicht",
    "GET_STARTER": "Bitte hol deinen starter um PKSM zu benutzen",
    "GPSS_BANNED": "Du wurdest aus dem GPSS verbannt!",
    "GPSS_COMMUNICATION_ERROR": "Fehler bei der Kommunikation mit GPSS:\n{:d}",
    "GPSS_TEMP_DISABLED": "Das Hochladen zum GPSS wurde vorübergehend deaktiviert!",
    "HTTP_OFFLINE": "Der Server ist offline!",
    "HTTP_UNKNOWN_ERROR": "Eine unbekannte HTTP Antwort",
    "INPUT_INVALID": "Ungültige Eingabe",
    "INPUT_TOO_SHORT": "Eingabe zu kurz",
    "INVALID_ABILITY": "Ungültige Fähigkeit",
    "INVALID_BALL": "Ungültiger Ball",
    "INVALID_FORM": "Ungültige Form",
    "INVALID_GAME": "Ungültiges Spiel",
    "INVALID_HP": "Ungültige Kraftreserve",
    "INVALID_ITEM": "Ungültiges Item",
    "INVALID_LOCATION": "Ungültiger Ort",
    "INVALID_MOVE": "Ungültige Attacke",
    "INVALID_NATURE": "Ungültiges Wesen",
    "INVALID_SPECIES": "Ungültige Spezies",
    "LEGALIZE_IN_QUEUE": "Dein vorheriges Pokémon gibt unserem Server einige Probleme",
    "LGPE_HAS_TM": "Du hast diese TM bereits!",
    "LGPE_NO_PARTY_SLOT": "Kein freier Slot gefunden",
    "LGPE_TOO_MANY_PKM": "Zu viele Pokémon",
    "LOADER_CRITICAL_ERROR": "Unmöglicher Fehler ist passiert!",
    "NEED_ONE_POKEMON": "Du musst mindestens ein Pokémon haben",
    "NOT_A_BUG": "Dies ist kein Bug.",
    "NO_DUPES": "Duplikate sind nicht erlaubt.",
    "NO_PARTY_EMPTY": "Kann Party nicht leeren!",
    "NO_TRANSFER_PATH": "Keine Möglichkeit, zwischen den Generationen zu transferieren.",
    "NO_TRANSFER_PATH_SINGLE": "Keine Möglichkeit, zwischen den Generationen zu transferieren:\n{:s}->{:s}",
    "NO_WONDERCARDS": "No wonder cards present",
    "NS_POKEMON?": "N's Pokémon?",
    "NULL_TERMINATOR": "Null-Terminator",
    "OFFLINE_ERROR": "Fehler: Offline",
    "PROBLEM_LEGALIZED_LENGTH": "Bei der Legalisierung des Pokémon ist ein Problem aufgetreten.",
    "QR_WRONG_FORMAT": "Falsches format für QR!",
    "REPORT_THIS": "Bitte melde dies!",
    "REPORT_THIS_TO_FLAGBREW": "Melde dies FlagBrew",
    "SAVE_INVALID": "ist kein valider Speicherstand.",
    "SCRIPTS_EXECUTION_ERROR": "Fehler beim Skript ausführen!",
    "SCRIPTS_FAILED_OPEN": "Konnte Skript Datei nicht öffnen!",
    "SCRIPTS_INVALID": "Kein valides Skript!",
    "SCRIPTS_NOT_FOUND": "nicht gefunden!",
    "SHARE_ERROR_INCORRECT_VERSION": "Die empfangene Größe passt nicht zur Version!",
    "SHARE_FAILED_CHECK": "Pokemon hat einen wichtigen Test nicht bestanden!",
    "SHARE_INVALID_CODE": "Dein Code ist entweder falsch oder abgelaufen!",
    "SOCKET_ACCEPT_FAIL": "Akzeptieren des Sockets fehlgeschlagen.",
    "SOCKET_BIND_FAIL": "Binden des Sockets fehlgeschlagen.",
    "SOCKET_CONNECTION_FAIL": "Verbindung zum Socket fehlgeschlagen.",
    "SOCKET_CREATE_FAIL": "Erstellen des Sockets fehlgeschlagen.",
    "SOCKET_LISTEN_FAIL": "Socket belauschen fehlgeschlagen.",
    "STORAGE_BAD_ABILITY": "Unmögliche Fähigkeit",
    "STORAGE_BAD_BALL": "Unmöglicher Ball",
    "STORAGE_BAD_FORM": "Unmögliche Form",
    "STORAGE_BAD_ITEM": "Unmögliches Item",
    "STORAGE_BAD_MOVE": "Unmögliche Attacke",
    "STORAGE_BAD_SPECIES": "Unmögliche Spezies",
    "STORAGE_BAD_TRANFER": "Konnte Pokémon nicht übertragen:",
    "STORAGE_CHECKBACK": "Schau in ein paar Jahren noch mal nach.",
    "STORAGE_IMPLEMENTATION": "Funktion noch nicht verfügbar.",
    "THE_FUCK": "Warum zum Fick passiert das?",
    "TITLE_ID_NOT_FOUND": "Titel ID nicht gefunden.",
    "UPDATE_CHECK_ERROR_BAD_JSON_1": "Fehler bei der Update-Suche!",
    "UPDATE_CHECK_ERROR_BAD_JSON_2": "JSON fehlerhaft",
    "UPDATE_FOUND_BUT_FAILED_DOWNLOAD": "Update gefunden, konnte aber nicht runtergeladen werden.",
    "USE_INJECTOR_C": "Benutze das universal skript \"injector.c\"",
    "WC_LGPE": "LGPE Speicherstände speichern keine Wunderkarten!",
    "WRONG_SIZE": "Falsche Größe für dieses Spiel!"
}